LICENSE.txt
MANIFEST.in
README.rst
fview-plugin-writing.rst
fview.desktop
setup.py
start_fview.bat
stdeb.cfg
motmot/__init__.py
motmot.fview.egg-info/PKG-INFO
motmot.fview.egg-info/SOURCES.txt
motmot.fview.egg-info/dependency_links.txt
motmot.fview.egg-info/eager_resources.txt
motmot.fview.egg-info/entry_points.txt
motmot.fview.egg-info/namespace_packages.txt
motmot.fview.egg-info/top_level.txt
motmot.fview.egg-info/zip-safe
motmot/fview/__init__.py
motmot/fview/fly.ai
motmot/fview/fly.png
motmot/fview/fview-icon.xcf
motmot/fview/fview-icon.xpm
motmot/fview/fview.gif
motmot/fview/fview.py
motmot/fview/fview.xcf
motmot/fview/fview.xrc
motmot/fview/fview_fmf_replay.py
motmot/fview/fview_icon2.png
motmot/fview/fview_icon2.xcf
motmot/fview/plugin_manager.py
motmot/fview/traited_plugin.py
motmot/fview/traited_plugin_base.py
motmot/fview/version.py