Metadata-Version: 1.0
Name: motmot.fview
Version: 0.6.8
Summary: extensible camera viewer program (part of the motmot camera packages)
Home-page: http://code.astraw.com/projects/motmot/fview.html
Author: Andrew Straw
Author-email: strawman@astraw.com
License: BSD
Platform: UNKNOWN
